{
  "en": {

    "@metadata": {
      "locale": "en",
      "documentation": "Additional or replacement messages."
    },
    "performance.polarSpeed": {
      "shortName": "polar stw",
      "longName": "Polar Speed Through Water"
    },
    "performance.polarSpeedRatio": {
      "shortName": "polar %",
      "longName": "Polar Speed Ratio"
    },
    "performance.targetAngle": {
      "shortName": "target twa",
      "longName": "Polar target true wind angle"
    },
    "performance.targetSpeed": {
      "shortName": "target stw",
      "longName": "Polar target speed through water"
    },
    "performance.headingMagnetic": {
      "shortName": "tack dir",
      "longName": "Other tack direction"
    },
    "performance.leeway": {
      "shortName": "leeway",
      "longName": "Leeway angle"
    },
    "performance.ignore": {
      "shortName": "-",
      "longName": "Unused"
    }
  }

}
